aws_prototyping_sdk/__init__.py
aws_prototyping_sdk/py.typed
aws_prototyping_sdk/_jsii/__init__.py
aws_prototyping_sdk/_jsii/aws-prototyping-sdk@0.17.5.jsii.tgz
aws_prototyping_sdk/nx_monorepo/__init__.py
aws_prototyping_sdk/nx_monorepo/nx/__init__.py
aws_prototyping_sdk/pdk_nag/__init__.py
aws_prototyping_sdk/pipeline/__init__.py
aws_prototyping_sdk-0.17.5.dist-info/LICENSE
aws_prototyping_sdk-0.17.5.dist-info/METADATA
aws_prototyping_sdk-0.17.5.dist-info/WHEEL
aws_prototyping_sdk-0.17.5.dist-info/top_level.txt
aws_prototyping_sdk-0.17.5.dist-info/RECORD
